xingyunlib/PIL_extend.py
xingyunlib/__init__.py
xingyunlib/all.py
xingyunlib/code.py
xingyunlib/color.py
xingyunlib/data.py
xingyunlib/dsfAdmin.py
xingyunlib/err.py
xingyunlib/http_spider.py
xingyunlib/image.py
xingyunlib/mail.py
xingyunlib/print_format.py
xingyunlib/pygame_extend.py
xingyunlib/render.py
xingyunlib/spell.py
xingyunlib/tkinter_extend.py
xingyunlib/updata_yourpackage.py
xingyunlib/user.py
xingyunlib/venv_install.py
xingyunlib/xesapi.py
xingyunlib/xesapp.py
xingyunlib/xesuser.py
xingyunlib_user_bin-0.0.20201206.dist-info/METADATA
xingyunlib_user_bin-0.0.20201206.dist-info/WHEEL
xingyunlib_user_bin-0.0.20201206.dist-info/top_level.txt
xingyunlib_user_bin-0.0.20201206.dist-info/RECORD
