Metadata-Version: 2.1
Name: xingyunlib-user-bin
Version: 0.0.20201206
Summary: first
Home-page: UNKNOWN
Author: UNKNOWN
Author-email: UNKNOWN
License: BSD License
Platform: all
Classifier: Development Status :: 4 - Beta
Classifier: Operating System :: OS Independent
Classifier: Intended Audience :: Developers
Classifier: License :: OSI Approved :: BSD License
Classifier: Programming Language :: Python :: 3
Classifier: Topic :: Software Development :: Libraries
Requires-Dist: requests
